<annotation>
	<folder>my-project-name</folder>
	<filename>56.jpeg</filename>
	<path>/my-project-name/56.jpeg</path>
	<source>
		<database>Unspecified</database>
	</source>
	<size>
		<width>1176</width>
		<height>796</height>
		<depth>3</depth>
	</size>
	<object>
		<name>Halpha</name>
		<pose>Unspecified</pose>
		<truncated>Unspecified</truncated>
		<difficult>Unspecified</difficult>
		<bndbox>
			<xmin>89</xmin>
			<ymin>174</ymin>
			<xmax>300</xmax>
			<ymax>378</ymax>
		</bndbox>
	</object>
	<object>
		<name>Halpha</name>
		<pose>Unspecified</pose>
		<truncated>Unspecified</truncated>
		<difficult>Unspecified</difficult>
		<bndbox>
			<xmin>696</xmin>
			<ymin>296</ymin>
			<xmax>898</xmax>
			<ymax>405</ymax>
		</bndbox>
	</object>
</annotation>